mds_test_package_2020/adder.py
mds_test_package_2020-0.1.0.dist-info/WHEEL
mds_test_package_2020-0.1.0.dist-info/METADATA
mds_test_package_2020-0.1.0.dist-info/RECORD
