Metadata-Version: 2.1
Name: mds-test-package-2020
Version: 0.1.0
Summary: some description
Author: Mark Dunne
Author-email: markdunne@improbable.io
Requires-Python: >=3.8,<4.0
Classifier: Programming Language :: Python :: 3
Classifier: Programming Language :: Python :: 3.8
Classifier: Programming Language :: Python :: 3.9
Requires-Dist: numpy (>=1.19.4,<2.0.0)
